{
"type": "FeatureCollection",
"name": "Boston_Logan_Airport_4326",
"crs": { "type": "name", "properties": { "name": "urn:ogc:def:crs:OGC:1.3:CRS84" } },
"features": [
{ "type": "Feature", "properties": { "id": 1, "name": "Boston Logan Airport" }, "geometry": { "type": "Point", "coordinates": [ -71.019219220828575, 42.366144786067395 ] } }
]
}
